rgb/semafororgb.v
`timescale 1ns / 1ps
// ============================================================
// Smoke Test - Semaforo en LED RGB #6 (LD6) de la Zybo Z7
// Reloj: 125 MHz (pin K17)  ->  T_clk = 8 ns
// Secuencia: Rojo -> Amarillo -> Verde -> Amarillo -> (repite)
// Cada estado dura N_ESTADO ciclos (80e6 * 8 ns = 0.64 s en hardware)
//
// Mapeo segun el .xdc:  led[0] = R (V16)
//                       led[1] = B (M17)
//                       led[2] = G (F17)
//  => led = {G, B, R}
//
// N_ESTADO es un parametro para poder simular con valores pequenos.
// En sintesis se usa el valor por defecto (80e6).
// ============================================================
module Semaforo #(
    parameter integer N_ESTADO = 80000000
)(
    input            clk,
    output reg [2:0] led
    );

    localparam integer N_TOTAL = 4 * N_ESTADO;   // 320e6 en hardware

    // Colores codificados como {G, B, R}
    localparam [2:0] ROJO     = 3'b001;
    localparam [2:0] AMARILLO = 3'b101;          // R + G
    localparam [2:0] VERDE    = 3'b100;

    integer counter = 0;

    // Contador de ciclos: 0 ... N_TOTAL
    always @(posedge clk) begin
        if (counter >= N_TOTAL)
            counter <= 0;
        else
            counter <= counter + 1;
    end

    // Cambio de color en cada cuarto del periodo
    always @(posedge clk) begin
        if (counter == 0)
            led <= ROJO;
        else if (counter == N_ESTADO)
            led <= AMARILLO;
        else if (counter == 2*N_ESTADO)
            led <= VERDE;
        else if (counter == 3*N_ESTADO)
            led <= AMARILLO;
    end

endmodule

rgb/tb_semaforo.v
`timescale 1ns / 1ps
// ============================================================
// Testbench autoverificable del Semaforo
//  - Reloj de 125 MHz (8 ns), igual al de la Zybo Z7
//  - N_ESTADO reducido a 10 ciclos para que la simulacion sea corta
//  - Verifica: orden de colores y duracion de cada estado
// ============================================================
module tb_semaforo;

    localparam integer N_ESTADO = 10;
    localparam real    T_CLK    = 8.0;           // ns
    localparam integer N_CICLOS = 3;             // ciclos completos a verificar

    localparam [2:0] ROJO     = 3'b001;
    localparam [2:0] AMARILLO = 3'b101;
    localparam [2:0] VERDE    = 3'b100;

    reg        clk = 1'b0;
    wire [2:0] led;

    // Dispositivo bajo prueba
    Semaforo #(.N_ESTADO(N_ESTADO)) dut (
        .clk (clk),
        .led (led)
    );

    // Reloj de 125 MHz
    always #(T_CLK/2) clk = ~clk;

    // Secuencia esperada
    reg [2:0] esperado [0:3];
    initial begin
        esperado[0] = ROJO;
        esperado[1] = AMARILLO;
        esperado[2] = VERDE;
        esperado[3] = AMARILLO;
    end

    // Nombre del color para los mensajes
    function [63:0] nombre;
        input [2:0] c;
        case (c)
            ROJO:     nombre = "ROJO    ";
            AMARILLO: nombre = "AMARILLO";
            VERDE:    nombre = "VERDE   ";
            3'b010:   nombre = "AZUL    ";
            default:  nombre = "OTRO    ";
        endcase
    endfunction

    // Verificador: se ejecuta en cada cambio de led
    integer idx     = 0;
    integer errores = 0;
    real    t_ant   = 0.0;
    real    dur, dur_esp;

    always @(led) begin
        if (led !== 3'bxxx) begin
            // 1) Color
            if (led !== esperado[idx % 4]) begin
                $display("[%0.1f ns] ERROR: color %s, se esperaba %s",
                         $realtime, nombre(led), nombre(esperado[idx % 4]));
                errores = errores + 1;
            end else
                $display("[%0.1f ns] OK: %s", $realtime, nombre(led));

            // 2) Duracion del estado anterior
            if (idx > 0) begin
                dur = $realtime - t_ant;
                // El ultimo estado (2do amarillo) dura 1 ciclo mas porque
                // el contador cuenta de 0 a N_TOTAL inclusive
                dur_esp = (idx % 4 == 0) ? (N_ESTADO + 1) * T_CLK
                                         :  N_ESTADO      * T_CLK;
                if (dur != dur_esp) begin
                    $display("           ERROR: duracion %0.1f ns, se esperaba %0.1f ns",
                             dur, dur_esp);
                    errores = errores + 1;
                end else
                    $display("           duracion estado anterior = %0.1f ns", dur);
            end

            t_ant = $realtime;
            idx   = idx + 1;
        end
    end

    // Control de la simulacion
    initial begin
        $dumpfile("tb_semaforo.vcd");
        $dumpvars(0, tb_semaforo);

        wait (idx == 4*N_CICLOS + 1);   // N_CICLOS completos + regreso a rojo
        #(T_CLK);

        $display("--------------------------------------------");
        if (errores == 0)
            $display("SMOKE TEST (simulacion): PASO - %0d transiciones verificadas", idx);
        else
            $display("SMOKE TEST (simulacion): FALLO - %0d errores", errores);
        $display("--------------------------------------------");
        $finish;
    end

    // Tiempo maximo por si el DUT no cambia nunca
    initial begin
        #(T_CLK * (4*N_ESTADO + 1) * (N_CICLOS + 2));
        $display("TIMEOUT: el LED no completo la secuencia (%0d transiciones)", idx);
        $finish;
    end

endmodule

rgb/tb_semaforo.vcd
$date
	Sun Sep 27 00:24:24 2026
$end
$version
	Icarus Verilog
$end
$timescale
	1ps
$end
$scope module tb_semaforo $end
$var wire 3 ! led [2:0] $end
$var parameter 3 " AMARILLO $end
$var parameter 32 # N_CICLOS $end
$var parameter 32 $ N_ESTADO $end
$var parameter 3 % ROJO $end
$var real 1 & T_CLK $end
$var parameter 3 ' VERDE $end
$var reg 1 ( clk $end
$var real 1 ) dur $end
$var real 1 * dur_esp $end
$var integer 32 + errores [31:0] $end
$var integer 32 , idx [31:0] $end
$var real 1 - t_ant $end
$scope function nombre $end
$var reg 3 . c [2:0] $end
$upscope $end
$scope module dut $end
$var wire 1 ( clk $end
$var parameter 3 / AMARILLO $end
$var parameter 32 0 N_ESTADO $end
$var parameter 32 1 N_TOTAL $end
$var parameter 3 2 ROJO $end
$var parameter 3 3 VERDE $end
$var reg 3 4 led [2:0] $end
$var integer 32 5 counter [31:0] $end
$upscope $end
$upscope $end
$enddefinitions $end
$comment Show the parameter values. $end
$dumpall
b100 3
b1 2
b101000 1
b1010 0
b101 /
b100 '
r8 &
b1 %
b1010 $
b11 #
b101 "
$end
#0
$dumpvars
b0 5
bx 4
bx .
r0 -
b0 ,
b0 +
r0 *
r0 )
0(
bx !
$end
#4000
b1 ,
r4 -
b1 .
b1 5
b1 !
b1 4
1(
#8000
0(
#12000
b10 5
1(
#16000
0(
#20000
b11 5
1(
#24000
0(
#28000
b100 5
1(
#32000
0(
#36000
b101 5
1(
#40000
0(
#44000
b110 5
1(
#48000
0(
#52000
b111 5
1(
#56000
0(
#60000
b1000 5
1(
#64000
0(
#68000
b1001 5
1(
#72000
0(
#76000
b1010 5
1(
#80000
0(
#84000
b10 ,
r84 -
r80 *
r80 )
b101 .
b1011 5
b101 !
b101 4
1(
#88000
0(
#92000
b1100 5
1(
#96000
0(
#100000
b1101 5
1(
#104000
0(
#108000
b1110 5
1(
#112000
0(
#116000
b1111 5
1(
#120000
0(
#124000
b10000 5
1(
#128000
0(
#132000
b10001 5
1(
#136000
0(
#140000
b10010 5
1(
#144000
0(
#148000
b10011 5
1(
#152000
0(
#156000
b10100 5
1(
#160000
0(
#164000
b11 ,
r164 -
b100 .
b10101 5
b100 !
b100 4
1(
#168000
0(
#172000
b10110 5
1(
#176000
0(
#180000
b10111 5
1(
#184000
0(
#188000
b11000 5
1(
#192000
0(
#196000
b11001 5
1(
#200000
0(
#204000
b11010 5
1(
#208000
0(
#212000
b11011 5
1(
#216000
0(
#220000
b11100 5
1(
#224000
0(
#228000
b11101 5
1(
#232000
0(
#236000
b11110 5
1(
#240000
0(
#244000
b100 ,
r244 -
b101 .
b11111 5
b101 !
b101 4
1(
#248000
0(
#252000
b100000 5
1(
#256000
0(
#260000
b100001 5
1(
#264000
0(
#268000
b100010 5
1(
#272000
0(
#276000
b100011 5
1(
#280000
0(
#284000
b100100 5
1(
#288000
0(
#292000
b100101 5
1(
#296000
0(
#300000
b100110 5
1(
#304000
0(
#308000
b100111 5
1(
#312000
0(
#316000
b101000 5
1(
#320000
0(
#324000
b0 5
1(
#328000
0(
#332000
b101 ,
r332 -
r88 *
r88 )
b1 .
b1 !
b1 4
b1 5
1(
#336000
0(
#340000
b10 5
1(
#344000
0(
#348000
b11 5
1(
#352000
0(
#356000
b100 5
1(
#360000
0(
#364000
b101 5
1(
#368000
0(
#372000
b110 5
1(
#376000
0(
#380000
b111 5
1(
#384000
0(
#388000
b1000 5
1(
#392000
0(
#396000
b1001 5
1(
#400000
0(
#404000
b1010 5
1(
#408000
0(
#412000
b110 ,
r412 -
r80 *
r80 )
b101 .
b101 !
b101 4
b1011 5
1(
#416000
0(
#420000
b1100 5
1(
#424000
0(
#428000
b1101 5
1(
#432000
0(
#436000
b1110 5
1(
#440000
0(
#444000
b1111 5
1(
#448000
0(
#452000
b10000 5
1(
#456000
0(
#460000
b10001 5
1(
#464000
0(
#468000
b10010 5
1(
#472000
0(
#476000
b10011 5
1(
#480000
0(
#484000
b10100 5
1(
#488000
0(
#492000
b111 ,
r492 -
b100 .
b100 !
b100 4
b10101 5
1(
#496000
0(
#500000
b10110 5
1(
#504000
0(
#508000
b10111 5
1(
#512000
0(
#516000
b11000 5
1(
#520000
0(
#524000
b11001 5
1(
#528000
0(
#532000
b11010 5
1(
#536000
0(
#540000
b11011 5
1(
#544000
0(
#548000
b11100 5
1(
#552000
0(
#556000
b11101 5
1(
#560000
0(
#564000
b11110 5
1(
#568000
0(
#572000
b1000 ,
r572 -
b101 .
b101 !
b101 4
b11111 5
1(
#576000
0(
#580000
b100000 5
1(
#584000
0(
#588000
b100001 5
1(
#592000
0(
#596000
b100010 5
1(
#600000
0(
#604000
b100011 5
1(
#608000
0(
#612000
b100100 5
1(
#616000
0(
#620000
b100101 5
1(
#624000
0(
#628000
b100110 5
1(
#632000
0(
#636000
b100111 5
1(
#640000
0(
#644000
b101000 5
1(
#648000
0(
#652000
b0 5
1(
#656000
0(
#660000
b1001 ,
r660 -
r88 *
r88 )
b1 .
b1 5
b1 !
b1 4
1(
#664000
0(
#668000
b10 5
1(
#672000
0(
#676000
b11 5
1(
#680000
0(
#684000
b100 5
1(
#688000
0(
#692000
b101 5
1(
#696000
0(
#700000
b110 5
1(
#704000
0(
#708000
b111 5
1(
#712000
0(
#716000
b1000 5
1(
#720000
0(
#724000
b1001 5
1(
#728000
0(
#732000
b1010 5
1(
#736000
0(
#740000
b1010 ,
r740 -
r80 *
r80 )
b101 .
b1011 5
b101 !
b101 4
1(
#744000
0(
#748000
b1100 5
1(
#752000
0(
#756000
b1101 5
1(
#760000
0(
#764000
b1110 5
1(
#768000
0(
#772000
b1111 5
1(
#776000
0(
#780000
b10000 5
1(
#784000
0(
#788000
b10001 5
1(
#792000
0(
#796000
b10010 5
1(
#800000
0(
#804000
b10011 5
1(
#808000
0(
#812000
b10100 5
1(
#816000
0(
#820000
b1011 ,
r820 -
b100 .
b10101 5
b100 !
b100 4
1(
#824000
0(
#828000
b10110 5
1(
#832000
0(
#836000
b10111 5
1(
#840000
0(
#844000
b11000 5
1(
#848000
0(
#852000
b11001 5
1(
#856000
0(
#860000
b11010 5
1(
#864000
0(
#868000
b11011 5
1(
#872000
0(
#876000
b11100 5
1(
#880000
0(
#884000
b11101 5
1(
#888000
0(
#892000
b11110 5
1(
#896000
0(
#900000
b1100 ,
r900 -
b101 .
b11111 5
b101 !
b101 4
1(
#904000
0(
#908000
b100000 5
1(
#912000
0(
#916000
b100001 5
1(
#920000
0(
#924000
b100010 5
1(
#928000
0(
#932000
b100011 5
1(
#936000
0(
#940000
b100100 5
1(
#944000
0(
#948000
b100101 5
1(
#952000
0(
#956000
b100110 5
1(
#960000
0(
#964000
b100111 5
1(
#968000
0(
#972000
b101000 5
1(
#976000
0(
#980000
b0 5
1(
#984000
0(
#988000
b1101 ,
r988 -
r88 *
r88 )
b1 .
b1 !
b1 4
b1 5
1(
#992000
0(
#996000
b10 5
1(
